pulumi_crypto/__init__.py
pulumi_crypto/__main__.py
pulumi_crypto/constants.py
pulumi_crypto/exceptions.py
pulumi_crypto/internal_types.py
pulumi_crypto/passphrase_cipher.py
pulumi_crypto/py.typed
pulumi_crypto/util.py
pulumi_crypto/version.py
pulumi_crypto-1.1.0.dist-info/entry_points.txt
pulumi_crypto-1.1.0.dist-info/LICENSE
pulumi_crypto-1.1.0.dist-info/WHEEL
pulumi_crypto-1.1.0.dist-info/METADATA
pulumi_crypto-1.1.0.dist-info/RECORD
