Metadata-Version: 2.1
Name: pulumi-crypto
Version: 1.1.0
Summary: Python implementation of Pulumi passphrase encryption/decryption
Home-page: https://github.com/sammck/pulumi-crypto
License: MIT
Keywords: password,passphrase,secret,Pulumi,crypto,encryption,decryption
Author: Sam McKelvie
Author-email: dev@mckelvie.org
Requires-Python: >=3.7,<4.0
Classifier: License :: OSI Approved :: MIT License
Classifier: Programming Language :: Python :: 3
Classifier: Programming Language :: Python :: 3.10
Classifier: Programming Language :: Python :: 3.7
Classifier: Programming Language :: Python :: 3.8
Classifier: Programming Language :: Python :: 3.9
Requires-Dist: PyYAML (>=6.0,<7.0)
Requires-Dist: Pygments (>=2.12.0,<3.0.0)
Requires-Dist: pycryptodomex (>=3.14.1,<4.0.0)
Project-URL: Repository, https://github.com/sammck/pulumi-crypto.git
